[
    {
        "id": "a3d6ae2sys21a-h1",
        "type": "hint",
        "dependencies": [],
        "title": "Compare Slopes and Intercepts",
        "text": "We will compare the slopes and intercepts of the two lines: image1",
        "variabilization": {},
        "oer": "https://OATutor.io <OATutor>",
        "license": "https://creativecommons.org/licenses/by/4.0/ <CC BY 4.0>",
        "speech": "We will compare the slopes and intercepts of the two lines: image1",
        "math": [
            ""
        ],
        "pacedSpeech": [
            "We will compare the slopes and intercepts of the two lines: image1"
        ]
    },
    {
        "id": "a3d6ae2sys21a-h2",
        "type": "hint",
        "dependencies": [
            "a3d6ae2sys21a-h1"
        ],
        "title": "Slope-Intercept Form",
        "text": "Write the first equation in slope-intercept form:\\n$$5x+3y=4$$\\n$$3y=-5x+4$$\\n$$\\frac{3y}{3}=\\frac{\\left(-5x+4\\right)}{3}$$\\n$$y=\\frac{-5}{3} x+\\frac{4}{3}$$",
        "variabilization": {},
        "oer": "https://OATutor.io <OATutor>",
        "license": "https://creativecommons.org/licenses/by/4.0/ <CC BY 4.0>",
        "speech": "Write the first equation in slope-intercept form:\\n 5 x plus 3 y is equal to, 4 \\n 3 y, is equal to negative 5 x, plus 4 \\n, fraction, 3 y, over 3,  is equal to fraction, parentheses, negative 5 x, plus 4, , over 3,  \\n y is equal to fraction, negative 5, over 3,  x plus 4 thirds",
        "math": [
            "$$5x+3y=4$$",
            "$$3y=-5x+4$$",
            "$$\\frac{3y}{3}=\\frac{\\left(-5x+4\\right)}{3}$$",
            "$$y=\\frac{-5}{3} x+\\frac{4}{3}$$"
        ],
        "pacedSpeech": [
            "Write the first equation in slope-intercept form:  5 x plus 3 y is equal to, 4 ",
            "  3 y, is equal to negative 5 x, plus 4 ",
            " , fraction, 3 y, over 3,  is equal to fraction, , negative 5 x, plus 4, , over 3,  ",
            "  y is equal to fraction, negative 5, over 3,  x plus 4 thirds"
        ]
    },
    {
        "id": "a3d6ae2sys21a-h3",
        "type": "scaffold",
        "problemType": "TextBox",
        "answerType": "arithmetic",
        "hintAnswer": [
            "$$\\frac{-5}{3}$$"
        ],
        "dependencies": [
            "a3d6ae2sys21a-h2"
        ],
        "title": "Identify the Slope",
        "text": "What is $$m$$ in the equation?",
        "variabilization": {},
        "oer": "https://OATutor.io <OATutor>",
        "license": "https://creativecommons.org/licenses/by/4.0/ <CC BY 4.0>",
        "speech": "What is  m  in the equation?",
        "math": [
            "$$m$$"
        ],
        "pacedSpeech": [
            "What is   m ",
            " in the equation?"
        ]
    },
    {
        "id": "a3d6ae2sys21a-h4",
        "type": "scaffold",
        "problemType": "TextBox",
        "answerType": "arithmetic",
        "hintAnswer": [
            "$$\\frac{4}{3}$$"
        ],
        "dependencies": [
            "a3d6ae2sys21a-h3"
        ],
        "title": "Identify y-intercept",
        "text": "What is $$b$$ in the equation?",
        "variabilization": {},
        "oer": "https://OATutor.io <OATutor>",
        "license": "https://creativecommons.org/licenses/by/4.0/ <CC BY 4.0>",
        "speech": "What is b  in the equation?",
        "math": [
            "$$b$$"
        ],
        "pacedSpeech": [
            "What is  b ",
            " in the equation?"
        ]
    },
    {
        "id": "a3d6ae2sys21a-h5",
        "type": "hint",
        "dependencies": [
            "a3d6ae2sys21a-h4"
        ],
        "title": "Slope-Intercept Form",
        "text": "Write the second equation in slope-intercept form:\\n$$2x-3y=5$$\\n$$-3y=-2x+5$$\\n$$\\frac{-3y}{-3}=\\frac{\\left(-2x+5\\right)}{-3}$$\\n$$y=\\frac{2}{3} x-\\frac{5}{3}$$",
        "variabilization": {},
        "oer": "https://OATutor.io <OATutor>",
        "license": "https://creativecommons.org/licenses/by/4.0/ <CC BY 4.0>",
        "speech": "Write the second equation in slope-intercept form:\\n 2 x minus 3 y is equal to, 5 \\n negative 3 y is equal to negative 2 x, plus 5 \\n fraction, negative 3 y, over, negative 3,  is equal to fraction, parentheses, negative 2 x, plus 5, , over, negative 3,  \\n y is equal to, 2 thirds x minus 5 thirds",
        "math": [
            "$$2x-3y=5$$",
            "$$-3y=-2x+5$$",
            "$$\\frac{-3y}{-3}=\\frac{\\left(-2x+5\\right)}{-3}$$",
            "$$y=\\frac{2}{3} x-\\frac{5}{3}$$"
        ],
        "pacedSpeech": [
            "Write the second equation in slope-intercept form:  2 x minus 3 y is equal to, 5 ",
            "  negative 3 y is equal to negative 2 x, plus 5 ",
            "  fraction, negative 3 y, over, negative 3,  is equal to fraction, , negative 2 x, plus 5, , over, negative 3,  ",
            "  y is equal to, 2 thirds x minus 5 thirds"
        ]
    },
    {
        "id": "a3d6ae2sys21a-h6",
        "type": "scaffold",
        "problemType": "TextBox",
        "answerType": "arithmetic",
        "hintAnswer": [
            "$$\\frac{2}{3}$$"
        ],
        "dependencies": [
            "a3d6ae2sys21a-h5"
        ],
        "title": "Identify the Slope",
        "text": "What is $$m$$ in the equation?",
        "variabilization": {},
        "oer": "https://OATutor.io <OATutor>",
        "license": "https://creativecommons.org/licenses/by/4.0/ <CC BY 4.0>",
        "speech": "What is  m  in the equation?",
        "math": [
            "$$m$$"
        ],
        "pacedSpeech": [
            "What is   m ",
            " in the equation?"
        ]
    },
    {
        "id": "a3d6ae2sys21a-h7",
        "type": "scaffold",
        "problemType": "TextBox",
        "answerType": "arithmetic",
        "hintAnswer": [
            "$$\\frac{-5}{3}$$"
        ],
        "dependencies": [
            "a3d6ae2sys21a-h6"
        ],
        "title": "Identify y-intercept",
        "text": "What is $$b$$ in the equation?",
        "variabilization": {},
        "oer": "https://OATutor.io <OATutor>",
        "license": "https://creativecommons.org/licenses/by/4.0/ <CC BY 4.0>",
        "speech": "What is  b  in the equation?",
        "math": [
            "$$b$$"
        ],
        "pacedSpeech": [
            "What is   b ",
            " in the equation?"
        ]
    },
    {
        "id": "a3d6ae2sys21a-h8",
        "type": "hint",
        "dependencies": [
            "a3d6ae2sys21a-h3",
            "a3d6ae2sys21a-h4",
            "a3d6ae2sys21a-h6",
            "a3d6ae2sys21a-h7"
        ],
        "title": "Intersecting Lines",
        "text": "Since the slopes are different, the lines intersect.",
        "variabilization": {},
        "oer": "https://OATutor.io <OATutor>",
        "license": "https://creativecommons.org/licenses/by/4.0/ <CC BY 4.0>",
        "speech": "Since the slopes are different, the lines intersect.",
        "math": [
            ""
        ],
        "pacedSpeech": [
            "Since the slopes are different, the lines intersect."
        ]
    },
    {
        "id": "a3d6ae2sys21a-h9",
        "type": "hint",
        "dependencies": [
            "a3d6ae2sys21a-h8"
        ],
        "title": "Intersecting Lines",
        "text": "A system of equations whose graphs are intersect has $$1$$ solution.",
        "variabilization": {},
        "oer": "https://OATutor.io <OATutor>",
        "license": "https://creativecommons.org/licenses/by/4.0/ <CC BY 4.0>",
        "speech": "A system of equations whose graphs are intersect has  1  solution.",
        "math": [
            "$$1$$"
        ],
        "pacedSpeech": [
            "A system of equations whose graphs are intersect has   1 ",
            " solution."
        ]
    }
]