[
    {
        "id": "ac541bdIntroPhy17a-h1",
        "type": "hint",
        "dependencies": [],
        "title": "Breaking down the question",
        "text": "Follow the units while converting",
        "variabilization": {},
        "oer": "https://OATutor.io <OATutor>",
        "license": "https://creativecommons.org/licenses/by/4.0/ <CC BY 4.0>"
    },
    {
        "id": "ac541bdIntroPhy17a-h2",
        "type": "scaffold",
        "problemType": "TextBox",
        "answerType": "arithmetic",
        "hintAnswer": [
            "$$525600$$"
        ],
        "dependencies": [
            "ac541bdIntroPhy17a-h1"
        ],
        "title": "Sub-questions",
        "text": "How many minutes in $$1$$ year?",
        "variabilization": {},
        "oer": "https://OATutor.io <OATutor>",
        "license": "https://creativecommons.org/licenses/by/4.0/ <CC BY 4.0>"
    },
    {
        "id": "ac541bdIntroPhy17a-h3",
        "type": "scaffold",
        "problemType": "TextBox",
        "answerType": "arithmetic",
        "hintAnswer": [
            "$$36792000$$"
        ],
        "dependencies": [
            "ac541bdIntroPhy17a-h2"
        ],
        "title": "Sub-questions",
        "text": "How many minutes in $$70$$ years?",
        "variabilization": {},
        "oer": "https://OATutor.io <OATutor>",
        "license": "https://creativecommons.org/licenses/by/4.0/ <CC BY 4.0>"
    },
    {
        "id": "ac541bdIntroPhy17a-h4",
        "type": "scaffold",
        "problemType": "TextBox",
        "answerType": "arithmetic",
        "hintAnswer": [
            "$$2.2$$ * $${10}^9$$"
        ],
        "dependencies": [
            "ac541bdIntroPhy17a-h3"
        ],
        "title": "Combining",
        "text": "How many hearbeats in $$70$$ years given the $$\\frac{beats}{min}$$? (Round your answer to two signifcant figures)",
        "variabilization": {},
        "oer": "https://OATutor.io <OATutor>",
        "license": "https://creativecommons.org/licenses/by/4.0/ <CC BY 4.0>"
    }
]