{
    "id": "ad70fe4real21a",
    "stepAnswer": [
        "$$-2$$, $$-4$$, $$-6$$, $$-8$$"
    ],
    "problemType": "MultipleChoice",
    "stepTitle": "if f(x) has the following points, $$(2,1)$$, $$(4,3)$$, $$(6,7)$$, and $$(8,11)$$ and g(x) $$=$$ $$f(-x)$$, find the $$x$$ values of g(x).",
    "stepBody": "",
    "answerType": "string",
    "variabilization": {},
    "answerLatex": "$$-2$$, $$-4$$, $$-6$$, $$-8$$",
    "choices": [
        "$$-2$$, $$-4$$, $$-6$$, $$-8$$",
        "$$-2$$, $$-4$$, $$6$$, $$8$$",
        "$$2$$, $$4$$, $$-6$$, $$-8$$",
        "$$2$$, $$4$$, $$6$$, $$-8$$"
    ]
}