[
    {
        "id": "af3a09cmomentum7a-h1",
        "type": "hint",
        "dependencies": [],
        "title": "Professional Application",
        "text": "Consider the relationship between force, impulse, and momentum.",
        "variabilization": {},
        "oer": "https://OATutor.io <OATutor>",
        "license": ""
    },
    {
        "id": "af3a09cmomentum7a-h2",
        "type": "hint",
        "dependencies": [
            "af3a09cmomentum7a-h1"
        ],
        "title": "Professional Application",
        "text": "Utilize the impulse-momentum theorem to relate the impulse, force, and time of impact.",
        "variabilization": {},
        "oer": "https://OATutor.io <OATutor>",
        "license": ""
    }
]