[
    {
        "id": "a8ad46flog23a-h1",
        "type": "hint",
        "dependencies": [],
        "title": "Match Bases",
        "text": "With all terms containing same log base, the log can be removed, so it becomes $$x^2+3=4x$$. Solve for $$x$$.",
        "variabilization": {},
        "oer": "https://OATutor.io <OATutor>",
        "license": "https://creativecommons.org/licenses/by/4.0/ <CC BY 4.0>",
        "speech": "With all terms containing same log base, the log can be removed, so it becomes  x squared plus 3, is equal to, 4 x . Solve for  x .",
        "math": [
            "$$x^2+3=4x$$",
            "$$x$$"
        ],
        "pacedSpeech": [
            "With all terms containing same log base, the log can be removed, so it becomes   x squared plus 3, is equal to, 4 x ",
            ". Solve for   x"
        ]
    },
    {
        "id": "a8ad46flog23a-h2",
        "type": "hint",
        "dependencies": [
            "a8ad46flog23a-h1"
        ],
        "title": "Solve for $$x$$",
        "text": "We can simplify into $$x^2-4x+3=0$$ and solve for $$x$$. We can factor the quadratic get $$\\left(x-1\\right) \\left(x-3\\right)=0$$ which have $$x=1$$ or $$x=3$$ as solutions.",
        "variabilization": {},
        "oer": "https://OATutor.io <OATutor>",
        "license": "https://creativecommons.org/licenses/by/4.0/ <CC BY 4.0>",
        "speech": "We can simplify into  x squared minus 4 x plus 3 is equal to 0  and solve for  x . We can factor the quadratic get  parentheses x minus 1,  times, parentheses x minus 3,  is equal to 0  which have  x, is equal to 1  or  x, is equal to 3  as solutions.",
        "math": [
            "$$x^2-4x+3=0$$",
            "$$x$$",
            "$$\\left(x-1\\right) \\left(x-3\\right)=0$$",
            "$$x=1$$",
            "$$x=3$$"
        ],
        "pacedSpeech": [
            "We can simplify into   x squared minus 4 x plus 3 is equal to 0 ",
            " and solve for   x ",
            ". We can factor the quadratic get    x minus 1,  times,  x minus 3,  is equal to 0 ",
            " which have   x, is equal to 1 ",
            " or   x, is equal to 3 ",
            " as solutions."
        ]
    },
    {
        "id": "a8ad46flog23a-h3",
        "type": "hint",
        "dependencies": [
            "a8ad46flog23a-h2"
        ],
        "title": "Check for Constrains",
        "text": "Given $$\\log_{a}\\left(b\\right)$$, $$b$$ can not be negative. Both $$1$$ and $$3$$ are non negative. Therefore $$x=1$$ and $$x=3$$ are solutions for this equation.",
        "variabilization": {},
        "oer": "https://OATutor.io <OATutor>",
        "license": "https://creativecommons.org/licenses/by/4.0/ <CC BY 4.0>",
        "speech": "Given  the log base a of b, ,  b  can not be negative. Both  1  and  3  are non negative. Therefore  x is equal to 1  and  x, is equal to 3  are solutions for this equation.",
        "math": [
            "$$\\log_{a}\\left(b\\right)$$",
            "$$b$$",
            "$$1$$",
            "$$3$$",
            "$$x=1$$",
            "$$x=3$$"
        ],
        "pacedSpeech": [
            "Given   the log base a of b, ",
            ",   b ",
            " can not be negative. Both   1 ",
            " and   3 ",
            " are non negative. Therefore   x is equal to 1 ",
            " and   x, is equal to 3 ",
            " are solutions for this equation."
        ]
    }
]