{
    "id": "a2bc7c0mentalhealth5a",
    "stepAnswer": [
        "a person\u2019s abilities in language, reading, writing, math, reasoning, knowledge, and memory"
    ],
    "problemType": "MultipleChoice",
    "stepTitle": "What is the conceptual domain?",
    "stepBody": "",
    "answerType": "string",
    "variabilization": {},
    "choices": [
        "a person\u2019s abilities in language, reading, writing, math, reasoning, knowledge, and memory",
        "a person\u2019s ability to conduct their activities of daily living through communication and independent living",
        "intellectual functioning that falls below an IQ of $$70$$ and starts before age eighteen",
        "a person\u2019s abilities in language, reading, writing, math, reasoning, knowledge, and memory",
        "the way a person learns and $$problem-solves$$"
    ]
}