[
    {
        "id": "a39b8a0def22a-h1",
        "type": "hint",
        "dependencies": [],
        "title": "Average Velocity Equation",
        "text": "The instantaneous velocity of both vehicles is given by the slope of the tangent line at $$t=4$$.",
        "variabilization": {},
        "oer": "",
        "license": ""
    },
    {
        "id": "a39b8a0def22a-s1",
        "type": "scaffold",
        "problemType": "MultipleChoice",
        "answerType": "string",
        "hintAnswer": [
            "g(t)"
        ],
        "dependencies": [
            "a39b8a0def22a-h1"
        ],
        "title": "Velocities of Vehicles",
        "text": "Is f(t) or g(t)'s slope greater when $$t=4$$?",
        "variabilization": {},
        "oer": "",
        "license": "",
        "choices": [
            "g(t)",
            "s(t)"
        ]
    }
]