{
    "id": "a8114b9stat14",
    "title": "Quantitative versus Qualitative",
    "body": "For the following exercises, identify the type of data that would be used to describe a response (quantitative discrete, quantitative continuous, or qualitative).",
    "variabilization": {},
    "oer": "https://openstax.org/details/books/introductory-statistics <OpenStax: Introductory Statistics>",
    "license": "https://creativecommons.org/licenses/by/4.0/ <CC BY 4.0>",
    "lesson": "1.2",
    "courseName": "Stats Demo"
}