[
    {
        "id": "afb3ccdlang1a-h1",
        "type": "hint",
        "dependencies": [],
        "title": "Checking for Divisibility",
        "text": "Is 5625 divisible by 2?",
        "variabilization": {}
    },
    {
        "id": "afb3ccdlang1a-h2",
        "type": "hint",
        "dependencies": [
            "afb3ccdlang1a-h1"
        ],
        "title": "Checking for Divisibility",
        "text": "Does it end in 0, 2, 4, 6 or 8? No. 5626 is not divisible by 2.",
        "variabilization": {}
    },
    {
        "id": "afb3ccdlang1a-h3",
        "type": "hint",
        "dependencies": [
            "afb3ccdlang1a-h2"
        ],
        "title": "Checking for Divisibility",
        "text": "Is 5625 divisible by 3?",
        "variabilization": {}
    },
    {
        "id": "afb3ccdlang1a-h4",
        "type": "scaffold",
        "problemType": "TextBox",
        "answerType": "arithmetic",
        "hintAnswer": [
            "18"
        ],
        "dependencies": [
            "afb3ccdlang1a-h3"
        ],
        "title": "Checking for Divisibility",
        "text": "What is the sum of the digits?",
        "variabilization": {}
    },
    {
        "id": "afb3ccdlang1a-h5",
        "type": "hint",
        "dependencies": [
            "afb3ccdlang1a-h4"
        ],
        "title": "Checking for Divisibility",
        "text": "5626 is divisible by 3.",
        "variabilization": {}
    },
    {
        "id": "afb3ccdlang1a-h6",
        "type": "hint",
        "dependencies": [
            "afb3ccdlang1a-h5"
        ],
        "title": "Checking for Divisibility",
        "text": "Is 5625 divisible by 5 or 10?",
        "variabilization": {}
    },
    {
        "id": "afb3ccdlang1a-h7",
        "type": "hint",
        "dependencies": [
            "afb3ccdlang1a-h6"
        ],
        "title": "Checking for Divisibility",
        "text": "The last digit is 5, it's divisible by 5 not by 10.",
        "variabilization": {}
    },
    {
        "id": "afb3ccdlang1a-h8",
        "type": "hint",
        "dependencies": [
            "afb3ccdlang1a-h7"
        ],
        "title": "Checking for Divisibility",
        "text": "Is 5625 divisible by 6?",
        "variabilization": {}
    },
    {
        "id": "afb3ccdlang1a-h9",
        "type": "hint",
        "dependencies": [
            "afb3ccdlang1a-h8"
        ],
        "title": "Checking for Divisibility",
        "text": "5626 is not divisible by 2, so it's not divisible by 6.",
        "variabilization": {}
    }
]