[
    {
        "id": "a8b6b9fLinear5a-h1",
        "type": "hint",
        "dependencies": [],
        "title": "Separate Constants and Variables on Either Side of the Equation",
        "text": "We must first simplify each side of the equation to get $$5a-15+5=-10$$.",
        "variabilization": {},
        "oer": "https://OATutor.io <OATutor>",
        "license": "https://creativecommons.org/licenses/by/4.0/ <CC BY 4.0>"
    },
    {
        "id": "a8b6b9fLinear5a-h2",
        "type": "hint",
        "dependencies": [],
        "title": "Simplify",
        "text": "Simply the left hand side to $$5a-10=-10$$",
        "variabilization": {},
        "oer": "https://OATutor.io <OATutor>",
        "license": "https://creativecommons.org/licenses/by/4.0/ <CC BY 4.0>"
    },
    {
        "id": "a8b6b9fLinear5a-h3",
        "type": "hint",
        "dependencies": [],
        "title": "Simplify",
        "text": "Organize the constant to the same side to obtain $$7n=14$$",
        "variabilization": {},
        "oer": "https://OATutor.io <OATutor>",
        "license": "https://creativecommons.org/licenses/by/4.0/ <CC BY 4.0>"
    },
    {
        "id": "a8b6b9fLinear5a-h4",
        "type": "hint",
        "dependencies": [],
        "title": "Division",
        "text": "We must make the coefficient of the variable equal to $$1$$, so we divide by $$5$$ on both sides to get $$a=0$$",
        "variabilization": {},
        "oer": "https://OATutor.io <OATutor>",
        "license": "https://creativecommons.org/licenses/by/4.0/ <CC BY 4.0>"
    }
]