{
    "id": "a590f38trigonometric7a",
    "stepAnswer": [
        "$$\\frac{3\\pi}{4}$$, $$\\frac{7\\pi}{4}$$"
    ],
    "problemType": "MultipleChoice",
    "stepTitle": "Identify all exact solutions to the equation 2(tanx+3)=5+tanx,0\\leq $$x<2\\pi$$.",
    "stepBody": "",
    "answerType": "string",
    "variabilization": {},
    "answerLatex": "$$\\frac{3\\pi}{4}$$, $$\\frac{7\\pi}{4}$$",
    "choices": [
        "$$\\frac{3\\pi}{4}$$, $$\\frac{7\\pi}{4}$$",
        "$$\\frac{\\pi}{4}$$, $$\\frac{5\\pi}{4}$$",
        "$$\\frac{3\\pi}{4}$$, $$\\frac{5\\pi}{4}$$",
        "$$\\frac{7\\pi}{4}$$, $$\\frac{\\pi}{4}$$"
    ]
}