[
    {
        "id": "a912db6arithmetic9a-h1",
        "type": "hint",
        "dependencies": [],
        "title": "Formula for Writing Arithmetic Sequences",
        "text": "Substitute given values into $$a_n=a_1+\\left(n-1\\right) d$$ to find terms of sequence.",
        "variabilization": {},
        "oer": "https://OATutor.io <OATutor>",
        "license": "https://creativecommons.org/licenses/by/4.0/ <CC BY 4.0>",
        "speech": "Substitute given values into  a sub n is equal to a sub 1 plus, parentheses n minus 1,  times d  to find terms of sequence.",
        "math": [
            "$$a_n=a_1+\\left(n-1\\right) d$$"
        ],
        "pacedSpeech": [
            "Substitute given values into   a sub n is equal to a sub 1 plus,  n minus 1,  times d ",
            " to find terms of sequence."
        ]
    },
    {
        "id": "a912db6arithmetic9a-h2",
        "type": "hint",
        "dependencies": [
            "a912db6arithmetic9a-h1"
        ],
        "title": "Substitute",
        "text": "Substitute given values into $$a_n=a_1+\\left(n-1\\right) d$$ to find terms of sequence.",
        "variabilization": {},
        "oer": "https://OATutor.io <OATutor>",
        "license": "https://creativecommons.org/licenses/by/4.0/ <CC BY 4.0>",
        "speech": "Substitute given values into  a sub n is equal to a sub 1 plus, parentheses n minus 1,  times d  to find terms of sequence.",
        "math": [
            "$$a_n=a_1+\\left(n-1\\right) d$$"
        ],
        "pacedSpeech": [
            "Substitute given values into   a sub n is equal to a sub 1 plus,  n minus 1,  times d ",
            " to find terms of sequence."
        ]
    },
    {
        "id": "a912db6arithmetic9a-h3",
        "type": "hint",
        "dependencies": [
            "a912db6arithmetic9a-h2"
        ],
        "title": "Substitute",
        "text": "The equation is $$a_n=4+5\\left(n-1\\right)$$ after substituting given values.",
        "variabilization": {},
        "oer": "https://OATutor.io <OATutor>",
        "license": "https://creativecommons.org/licenses/by/4.0/ <CC BY 4.0>",
        "speech": "The equation is  a sub n is equal to 4 plus, 5 times, parentheses n minus 1,   after substituting given values.",
        "math": [
            "$$a_n=4+5\\left(n-1\\right)$$"
        ],
        "pacedSpeech": [
            "The equation is   a sub n is equal to 4 plus, 5 times,  n minus 1,  ",
            " after substituting given values."
        ]
    },
    {
        "id": "a912db6arithmetic9a-h4",
        "type": "hint",
        "dependencies": [
            "a912db6arithmetic9a-h3"
        ],
        "title": "Substitute",
        "text": "Substitute $$4$$ for $$n$$ in equation to find the fourth term of the sequence.",
        "variabilization": {},
        "oer": "https://OATutor.io <OATutor>",
        "license": "https://creativecommons.org/licenses/by/4.0/ <CC BY 4.0>",
        "speech": "Substitute  4  for  n,  in equation to find the fourth term of the sequence.",
        "math": [
            "$$4$$",
            "$$n$$"
        ],
        "pacedSpeech": [
            "Substitute   4 ",
            " for   n, ",
            " in equation to find the fourth term of the sequence."
        ]
    },
    {
        "id": "a912db6arithmetic9a-h5",
        "type": "scaffold",
        "problemType": "TextBox",
        "answerType": "arithmetic",
        "hintAnswer": [
            "$$19$$"
        ],
        "dependencies": [
            "a912db6arithmetic9a-h4"
        ],
        "title": "Substitute",
        "text": "What is $$a_4$$?",
        "variabilization": {},
        "oer": "https://OATutor.io <OATutor>",
        "license": "https://creativecommons.org/licenses/by/4.0/ <CC BY 4.0>",
        "speech": "What is  a sub 4 ?",
        "math": [
            "$$a_4$$"
        ],
        "pacedSpeech": [
            "What is   a sub 4"
        ]
    }
]