{
    "id": "a2b6a8bcorr11a",
    "stepAnswer": [
        "Strong positive correlation"
    ],
    "problemType": "MultipleChoice",
    "stepTitle": "Decide the direction (positive or negative) and strength (weak, moderate, or strong) of the correlation",
    "stepBody": "##figure1.gif## ",
    "answerType": "string",
    "variabilization": {},
    "choices": [
        "Weak negative correlation",
        "Moderate positive correlation",
        "Strong positive correlation",
        "No correlation"
    ]
}