{
    "id": "a88c93efixedaxis17",
    "title": "Torque Producing an Angular Acceleration",
    "body": "A constant torque is applied to a rigid body whose moment of inertia is $$4.0$$ $$kg m^2$$ around the axis of rotation. The wheel starts from rest and attains an angular velocity of $$20.0$$ $$\\frac{rad}{s}$$ in $$10.0$$ s.",
    "variabilization": {},
    "oer": "https://openstax.org/books/university-physics-volume-1/pages/10-7-newtons-second-law-for-rotation",
    "license": "https://creativecommons.org/licenses/by/4.0/ <CC BY 4.0>",
    "lesson": "10. Fixed-Axis Rotation",
    "lessonId": "7FpFxmKN-oemN-iRunlrgAeA",
    "courseName": "OpenStax: University Physics"
}