{
    "id": "a96632dprediction1a",
    "stepAnswer": [
        "$250,120"
    ],
    "problemType": "MultipleChoice",
    "stepTitle": "An electronics retailer used regression to find a simple model to predict sales growth in the first quarter of the new year (January through March). The model is good for 90 days, where x is the day. The model can be written as follows: \u0177 $$=$$ 101.32 + 2.48x where \u0177 is in thousands of dollars. What would you predict the sales to be on day 60?",
    "stepBody": "",
    "answerType": "string",
    "variabilization": {},
    "choices": [
        "$250,120",
        "$255,120",
        "$250,000",
        "$250,620",
        "None of the above"
    ]
}