{
    "id": "a2ee4dfsql10a",
    "stepAnswer": [
        "It specifies the matching condition for combining records."
    ],
    "problemType": "MultipleChoice",
    "stepTitle": "What is the function of the ON portion of a JOIN clause?",
    "stepBody": "",
    "answerType": "string",
    "variabilization": {},
    "choices": [
        "It creates the name for the resulting combination.",
        "It limits the total number of output records.",
        "It specifies the matching condition for combining records."
    ]
}