[
    {
        "id": "ad4c99aLinEqua3a-h1",
        "type": "hint",
        "dependencies": [],
        "title": "The y-intercept of a line",
        "text": "The y-intercept is the point at which the line crosses the y-axis. On the y-axis, $$x$$ $$=$$ $$0$$.",
        "variabilization": {},
        "oer": "https://OATutor.io <OATutor>",
        "license": "https://creativecommons.org/licenses/by/4.0/ <CC BY 4.0>"
    },
    {
        "id": "ad4c99aLinEqua3a-h2",
        "type": "hint",
        "dependencies": [
            "ad4c99aLinEqua3a-h1"
        ],
        "title": "Identify the y-intercept",
        "text": "We can always identify the y-intercept when the line is in slope-intercept from, as it will always equal $$b$$.",
        "variabilization": {},
        "oer": "https://OATutor.io <OATutor>",
        "license": "https://creativecommons.org/licenses/by/4.0/ <CC BY 4.0>"
    }
]