[
    {
        "id": "ac3d94dProperties19a-h1",
        "type": "hint",
        "dependencies": [],
        "title": "Inverse Property of Addition",
        "text": "For any real number a, -a is the additive inverse of a.",
        "variabilization": {},
        "oer": "https://OATutor.io <OATutor>",
        "license": "https://creativecommons.org/licenses/by/4.0/ <CC BY 4.0>"
    },
    {
        "id": "ac3d94dProperties19a-h2",
        "type": "scaffold",
        "problemType": "TextBox",
        "answerType": "arithmetic",
        "hintAnswer": [
            "$$\\frac{-5}{8}$$"
        ],
        "dependencies": [
            "ac3d94dProperties19a-h1"
        ],
        "title": "Additive Inverse",
        "text": "What is the additive inverse of $$\\frac{5}{8}$$?",
        "variabilization": {},
        "oer": "https://OATutor.io <OATutor>",
        "license": "https://creativecommons.org/licenses/by/4.0/ <CC BY 4.0>"
    }
]