{
    "id": "ac541bdIntroPhy3a",
    "stepAnswer": [
        "length: 377 ft, width: 279 ft"
    ],
    "problemType": "MultipleChoice",
    "stepTitle": "Soccer fields vary in size. A large soccer field is 115 m long and 85 m wide. What are its dimensions in feet? (Assume that 1 meter equals 3.281 feet, round to the nearest whole number)",
    "stepBody": "",
    "answerType": "string",
    "variabilization": {},
    "choices": [
        "length: 377 ft, width: 279 ft",
        "length: 379 ft, width: 290 ft",
        "length: 380 ft, width: 282 ft",
        "length: 377 ft, width: 290 ft"
    ]
}